reqst/__init__.py
reqst/__main__.py
reqst/client.py
reqst/colorizer.py
reqst/formatter.py
reqst/reader.py
reqst/writer.py
reqst-0.1.2.dist-info/LICENSE
reqst-0.1.2.dist-info/METADATA
reqst-0.1.2.dist-info/WHEEL
reqst-0.1.2.dist-info/entry_points.txt
reqst-0.1.2.dist-info/top_level.txt
reqst-0.1.2.dist-info/RECORD
