Metadata-Version: 2.2
Name: reqst
Version: 0.1.2
Summary: A Python CLI program to send requests.
Home-page: https://github.com/hstoklosa/reqst
Author: hstoklosa
Author-email: hubert.stoklosa23@gmail.com
License: MIT
Classifier: License :: OSI Approved :: MIT License
Classifier: Programming Language :: Python :: 3
Requires-Python: >=3.10
License-File: LICENSE
Requires-Dist: requests
Requires-Dist: PyYAML
Requires-Dist: lxml
Requires-Dist: Pygments
Dynamic: author
Dynamic: author-email
Dynamic: classifier
Dynamic: description
Dynamic: description-content-type
Dynamic: home-page
Dynamic: license
Dynamic: requires-dist
Dynamic: requires-python
Dynamic: summary
